statemonad/__init__.py
statemonad/abc.py
statemonad/exceptions.py
statemonad/py.typed
statemonad/typing.py
statemonad/statemonad/__init__.py
statemonad/statemonad/from_.py
statemonad/statemonad/init.py
statemonad/statemonad/init.pyi
statemonad/statemonad/statemonad.py
statemonad/statemonad/statemonad.pyi
statemonad/statemonadtree/__init__.py
statemonad/statemonadtree/init.py
statemonad/statemonadtree/nodes.py
statemonad/statemonadtree/operations/__init__.py
statemonad/statemonadtree/operations/flatmapmixin.py
statemonad/statemonadtree/operations/frommixin.py
statemonad/statemonadtree/operations/getmixin.py
statemonad/statemonadtree/operations/mapmixin.py
statemonad/statemonadtree/operations/putmixin.py
statemonad/statemonadtree/operations/zipmixin.py
statemonad/utils/__init__.py
statemonad/utils/getstacklines.py
statemonad-0.0.5.dist-info/METADATA
statemonad-0.0.5.dist-info/WHEEL
statemonad-0.0.5.dist-info/licenses/LICENCE
statemonad-0.0.5.dist-info/RECORD
