Metadata-Version: 2.3
Name: statemonad
Version: 0.0.5
Summary: A library that encapsulates stateful computations into a monadic structure.
Project-URL: Homepage, https://github.com/MichaelSchneeberger/state-monad
Author-email: Michael Schneeberger <michael.schneeb@hotmail.com>
License-File: LICENCE
Requires-Python: >=3.12
Requires-Dist: dataclassabc>=0.0.12
